Face_Recognition/Face_Recognition.py
Face_Recognition/__init__.py
face_Recogniti1-0.0.1.1.dist-info/LICENSE
face_Recogniti1-0.0.1.1.dist-info/METADATA
face_Recogniti1-0.0.1.1.dist-info/WHEEL
face_Recogniti1-0.0.1.1.dist-info/top_level.txt
face_Recogniti1-0.0.1.1.dist-info/RECORD
